p537.cpython-37m-darwin.so
p537-1.0.10.dist-info/LICENSE
p537-1.0.10.dist-info/METADATA
p537-1.0.10.dist-info/WHEEL
p537-1.0.10.dist-info/entry_points.txt
p537-1.0.10.dist-info/top_level.txt
p537-1.0.10.dist-info/RECORD
