Metadata-Version: 2.1
Name: p537
Version: 1.0.10
Summary: A tiny platform-specific distribution with a console script.
Home-page: https://github.com/pex-tool/p537
Author: John Sirois
Author-email: john.sirois@gmail.com
License: Apache License, Version 2.0
Platform: UNKNOWN
Classifier: Intended Audience :: Developers
Classifier: License :: OSI Approved :: Apache Software License
Classifier: Operating System :: POSIX :: Linux
Classifier: Operating System :: MacOS :: MacOS X
Classifier: Operating System :: Microsoft :: Windows
Classifier: Programming Language :: Python :: 3.6
Classifier: Programming Language :: Python :: 3.7
Classifier: Programming Language :: Python :: 3.8
Classifier: Programming Language :: Python :: 3.9
Classifier: Programming Language :: Python :: 3.10
Classifier: Programming Language :: Python :: 3.11
Classifier: Programming Language :: Python :: 3.12
Classifier: Programming Language :: Python :: 3.13
Classifier: Programming Language :: Python :: 3.14
Classifier: Programming Language :: Python :: 3.14
Classifier: Programming Language :: Python :: 3.15
Requires-Python: >=3.6,<3.16
License-File: LICENSE
